LICENSE.txt
MANIFEST.in
README.md
setup.cfg
setup.py
nestshredder/__init__.py
nestshredder/pyshred_core.py
nestshredder/pyshred_util.py
nestshredder.egg-info/PKG-INFO
nestshredder.egg-info/SOURCES.txt
nestshredder.egg-info/dependency_links.txt
nestshredder.egg-info/requires.txt
nestshredder.egg-info/top_level.txt