Metadata-Version: 2.1
Name: nestshredder
Version: 0.5.3
Summary: A useful thing that will take nested JSONS and output something a touch more SQL-sensible
Home-page: https://github.com/Gadz00ks77/nestshredder/
Author: Chris Woodward
Author-email: chriswoodward77@googlemail.com
License: MIT
Download-URL: https://github.com/Gadz00ks77/nestshredder/archive/refs/tags/v0.5.3.tar.gz
Platform: UNKNOWN
License-File: LICENSE.txt
